activity_tracking/__init__.py
activity_tracking/admin.py
activity_tracking/apps.py
activity_tracking/decorators.py
activity_tracking/helpers.py
activity_tracking/middleware.py
activity_tracking/mixins.py
activity_tracking/models.py
activity_tracking/registry.py
activity_tracking/serializers.py
activity_tracking/settings.py
activity_tracking/setup.py
activity_tracking/signals.py
activity_tracking/tests.py
activity_tracking/urls.py
activity_tracking/utils.py
activity_tracking/views.py
activity_tracking/migrations/0001_initial.py
activity_tracking/migrations/__init__.py
django_activity_tracking-1.0.2.dist-info/licenses/LICENSE
django_activity_tracking-1.0.2.dist-info/METADATA
django_activity_tracking-1.0.2.dist-info/WHEEL
django_activity_tracking-1.0.2.dist-info/top_level.txt
django_activity_tracking-1.0.2.dist-info/RECORD
