Metadata-Version: 2.4
Name: django-activity-tracking
Version: 1.0.2
Summary: A plug-and-play Django app for tracking user activities
Author-email: Rajat Jog <rajatjog1294@gmail.com>
License-Expression: MIT
Project-URL: Homepage, https://github.com/RJ-Gamer/django-activity-tracking
Project-URL: Documentation, https://github.com/RJ-Gamer/django-activity-tracking#readme
Project-URL: Repository, https://github.com/RJ-Gamer/django-activity-tracking
Keywords: django,activity,tracking,audit,log
Classifier: Development Status :: 5 - Production/Stable
Classifier: Environment :: Web Environment
Classifier: Framework :: Django
Classifier: Framework :: Django :: 4.0
Classifier: Framework :: Django :: 4.1
Classifier: Framework :: Django :: 4.2
Classifier: Framework :: Django :: 5.0
Classifier: Intended Audience :: Developers
Classifier: Operating System :: OS Independent
Classifier: Programming Language :: Python :: 3
Classifier: Programming Language :: Python :: 3.8
Classifier: Programming Language :: Python :: 3.9
Classifier: Programming Language :: Python :: 3.10
Classifier: Programming Language :: Python :: 3.11
Classifier: Programming Language :: Python :: 3.12
Requires-Python: >=3.8
License-File: LICENSE
Requires-Dist: Django>=4.0
Requires-Dist: djangorestframework>=3.14
Dynamic: license-file
